muranoagent/app.py
muranoagent/__init__.py
muranoagent/exceptions.py
muranoagent/files_manager.py
muranoagent/script_runner.py
muranoagent/execution_plan_queue.py
muranoagent/version.py
muranoagent/execution_plan_runner.py
muranoagent/win32.py
muranoagent/opts.py
muranoagent/execution_result.py
muranoagent/openstack/__init__.py
muranoagent/openstack/common/__init__.py
muranoagent/openstack/common/systemd.py
muranoagent/openstack/common/eventlet_backdoor.py
muranoagent/openstack/common/local.py
muranoagent/openstack/common/importutils.py
muranoagent/openstack/common/timeutils.py
muranoagent/openstack/common/service.py
muranoagent/openstack/common/jsonutils.py
muranoagent/openstack/common/gettextutils.py
muranoagent/openstack/common/threadgroup.py
muranoagent/openstack/common/log.py
muranoagent/openstack/common/loopingcall.py
muranoagent/openstack/common/strutils.py
muranoagent/openstack/common/config/__init__.py
muranoagent/openstack/common/config/generator.py
muranoagent/executors/__init__.py
muranoagent/executors/chef_puppet_executor_base.py
muranoagent/executors/application/__init__.py
muranoagent/executors/chef/__init__.py
muranoagent/executors/puppet/__init__.py
muranoagent/tests/__init__.py
muranoagent/tests/unit/execution_plan.py
muranoagent/tests/unit/test_app.py
muranoagent/tests/unit/__init__.py
muranoagent/tests/unit/test_files_manager.py
muranoagent/tests/unit/base.py
muranoagent/tests/unit/test_agent.py
muranoagent/tests/unit/test_script_runner.py
muranoagent/tests/unit/executors/test_puppet.py
muranoagent/tests/unit/executors/__init__.py
muranoagent/tests/unit/executors/test_chef.py
muranoagent/common/__init__.py
muranoagent/common/config.py
muranoagent/common/messaging/__init__.py
muranoagent/common/messaging/mqclient.py
muranoagent/common/messaging/subscription.py
muranoagent/common/messaging/message.py
muranoagent/cmd/__init__.py
muranoagent/cmd/run.py
murano_agent-2015.1.0.dist-info/DESCRIPTION.rst
murano_agent-2015.1.0.dist-info/METADATA
murano_agent-2015.1.0.dist-info/WHEEL
murano_agent-2015.1.0.dist-info/top_level.txt
murano_agent-2015.1.0.dist-info/pbr.json
murano_agent-2015.1.0.dist-info/entry_points.txt
murano_agent-2015.1.0.dist-info/metadata.json
murano_agent-2015.1.0.dist-info/RECORD
