Metadata-Version: 2.0
Name: murano-agent
Version: 2015.1.0
Summary: Python Murano Agent
Home-page: htts://launchpad.net/murano
Author: Mirantis, Inc.
Author-email: openstack-dev@lists.openstack.org
License: Apache License, Version 2.0
Platform: UNKNOWN
Classifier: Development Status :: 5 - Production/Stable
Classifier: Environment :: OpenStack
Classifier: Intended Audience :: Developers
Classifier: Intended Audience :: Information Technology
Classifier: License :: OSI Approved :: Apache Software License
Classifier: Operating System :: OS Independent
Classifier: Programming Language :: Python
Requires-Dist: pbr (>=0.6,!=0.7,<1.0)
Requires-Dist: anyjson (>=0.3.3)
Requires-Dist: Babel (>=1.3)
Requires-Dist: eventlet (>=0.16.1,!=0.17.0)
Requires-Dist: iso8601 (>=0.1.9)
Requires-Dist: kombu (>=2.5.0)
Requires-Dist: oslo.config (>=1.9.3,<1.10.0)
Requires-Dist: PyYAML (>=3.1.0)
Requires-Dist: six (>=1.9.0)
Requires-Dist: stevedore (>=1.3.0,<1.4.0)
Requires-Dist: semantic-version (>=2.3.1)
Requires-Dist: bunch
Requires-Dist: gitpython
Requires-Dist: requests
